[
  {
    "FLD_DESC": "Gearchiveerd",
    "FIELD_NAME": "ADM_ARCH",
    "DBF_NAME": "ADM_LIST",
    "FIELD_LEN": 1,
    "FIELD_TYPE": "L",
    "INP_MAND": false,
    "FLD_FMT": "",
    "FLD_MASK": "",
    "COM_BLK": false,
    "CNG_DATE": "",
    "CNG_NR": 0,
    "CNG_USR": "",
    "INP_DATE": "",
    "PKY_TBL": "",
    "REC_CUST": false,
    "DCT_FLD_Id": 0
  },
  {
    "FLD_DESC": "Admin.code",
    "FIELD_NAME": "ADM_CODE",
    "DBF_NAME": "ADM_LIST",
    "FIELD_LEN": 10,
    "FIELD_TYPE": "C",
    "INP_MAND": true,
    "FLD_FMT": "!",
    "FLD_MASK": "",
    "COM_BLK": false,
    "CNG_DATE": "",
    "CNG_NR": 0,
    "CNG_USR": "",
    "INP_DATE": "",
    "PKY_TBL": "",
    "REC_CUST": false,
    "DCT_FLD_Id": 1
  },
  {
    "FLD_DESC": "Notitie administratie",
    "FIELD_NAME": "ADM_COMM",
    "DBF_NAME": "ADM_LIST",
    "FIELD_LEN": 4,
    "FIELD_TYPE": "M",
    "INP_MAND": false,
    "FLD_FMT": "",
    "FLD_MASK": "",
    "COM_BLK": false,
    "CNG_DATE": "",
    "CNG_NR": 0,
    "CNG_USR": "",
    "INP_DATE": "",
    "PKY_TBL": "",
    "REC_CUST": false,
    "DCT_FLD_Id": 2
  },
  {
    "FLD_DESC": "Admin.naam",
    "FIELD_NAME": "ADM_DESC",
    "DBF_NAME": "ADM_LIST",
    "FIELD_LEN": 40,
    "FIELD_TYPE": "C",
    "INP_MAND": true,
    "FLD_FMT": "",
    "FLD_MASK": "",
    "COM_BLK": false,
    "CNG_DATE": "",
    "CNG_NR": 0,
    "CNG_USR": "",
    "INP_DATE": "",
    "PKY_TBL": "",
    "REC_CUST": false,
    "DCT_FLD_Id": 3
  },
  {
    "FLD_DESC": "Mapnaam administratie",
    "FIELD_NAME": "ADM_DIR",
    "DBF_NAME": "ADM_LIST",
    "FIELD_LEN": 200,
    "FIELD_TYPE": "C",
    "INP_MAND": true,
    "FLD_FMT": "",
    "FLD_MASK": "",
    "COM_BLK": false,
    "CNG_DATE": "",
    "CNG_NR": 0,
    "CNG_USR": "",
    "INP_DATE": "",
    "PKY_TBL": "",
    "REC_CUST": false,
    "DCT_FLD_Id": 4
  },
  {
    "FLD_DESC": "Naam holding-administratie",
    "FIELD_NAME": "ADM_HOLD",
    "DBF_NAME": "ADM_LIST",
    "FIELD_LEN": 10,
    "FIELD_TYPE": "C",
    "INP_MAND": false,
    "FLD_FMT": "!",
    "FLD_MASK": "",
    "COM_BLK": false,
    "CNG_DATE": "",
    "CNG_NR": 0,
    "CNG_USR": "",
    "INP_DATE": "",
    "PKY_TBL": "",
    "REC_CUST": false,
    "DCT_FLD_Id": 5
  },
  {
    "FLD_DESC": "Naam holding-admin intern",
    "FIELD_NAME": "ADM_HOLD2",
    "DBF_NAME": "ADM_LIST",
    "FIELD_LEN": 10,
    "FIELD_TYPE": "C",
    "INP_MAND": false,
    "FLD_FMT": "!",
    "FLD_MASK": "",
    "COM_BLK": false,
    "CNG_DATE": "",
    "CNG_NR": 0,
    "CNG_USR": "",
    "INP_DATE": "",
    "PKY_TBL": "",
    "REC_CUST": false,
    "DCT_FLD_Id": 6
  },
  {
    "FLD_DESC": "Voorbeeldadministratie",
    "FIELD_NAME": "ADM_MODEL",
    "DBF_NAME": "ADM_LIST",
    "FIELD_LEN": 1,
    "FIELD_TYPE": "L",
    "INP_MAND": false,
    "FLD_FMT": "",
    "FLD_MASK": "",
    "COM_BLK": false,
    "CNG_DATE": "",
    "CNG_NR": 0,
    "CNG_USR": "",
    "INP_DATE": "",
    "PKY_TBL": "",
    "REC_CUST": false,
    "DCT_FLD_Id": 7
  },
  {
    "FLD_DESC": "Administratie vorig jaar",
    "FIELD_NAME": "ADM_PREV",
    "DBF_NAME": "ADM_LIST",
    "FIELD_LEN": 10,
    "FIELD_TYPE": "C",
    "INP_MAND": false,
    "FLD_FMT": "!",
    "FLD_MASK": "",
    "COM_BLK": false,
    "CNG_DATE": "",
    "CNG_NR": 0,
    "CNG_USR": "",
    "INP_DATE": "",
    "PKY_TBL": "",
    "REC_CUST": false,
    "DCT_FLD_Id": 8
  },
  {
    "FLD_DESC": "Administratie op andere vestiging",
    "FIELD_NAME": "ADM_REMOTE",
    "DBF_NAME": "ADM_LIST",
    "FIELD_LEN": 1,
    "FIELD_TYPE": "L",
    "INP_MAND": false,
    "FLD_FMT": "",
    "FLD_MASK": "",
    "COM_BLK": false,
    "CNG_DATE": "",
    "CNG_NR": 0,
    "CNG_USR": "",
    "INP_DATE": "",
    "PKY_TBL": "",
    "REC_CUST": false,
    "DCT_FLD_Id": 9
  },
  {
    "FLD_DESC": "Advies: organiseer administratie",
    "FIELD_NAME": "ADV_ORG",
    "DBF_NAME": "ADM_LIST",
    "FIELD_LEN": 1,
    "FIELD_TYPE": "L",
    "INP_MAND": false,
    "FLD_FMT": "",
    "FLD_MASK": "",
    "COM_BLK": false,
    "CNG_DATE": "",
    "CNG_NR": 0,
    "CNG_USR": "",
    "INP_DATE": "",
    "PKY_TBL": "",
    "REC_CUST": false,
    "DCT_FLD_Id": 10
  },
  {
    "FLD_DESC": "Administratiebestanden niet beperken",
    "FIELD_NAME": "ALL_TBL",
    "DBF_NAME": "ADM_LIST",
    "FIELD_LEN": 1,
    "FIELD_TYPE": "L",
    "INP_MAND": false,
    "FLD_FMT": "",
    "FLD_MASK": "",
    "COM_BLK": false,
    "CNG_DATE": "",
    "CNG_NR": 0,
    "CNG_USR": "",
    "INP_DATE": "",
    "PKY_TBL": "",
    "REC_CUST": false,
    "DCT_FLD_Id": 11
  },
  {
    "FLD_DESC": "Cliëntcode",
    "FIELD_NAME": "ATS_CODE",
    "DBF_NAME": "ADM_LIST",
    "FIELD_LEN": 20,
    "FIELD_TYPE": "C",
    "INP_MAND": false,
    "FLD_FMT": "",
    "FLD_MASK": "",
    "COM_BLK": false,
    "CNG_DATE": "",
    "CNG_NR": 0,
    "CNG_USR": "",
    "INP_DATE": "",
    "PKY_TBL": "",
    "REC_CUST": false,
    "DCT_FLD_Id": 12
  },
  {
    "FLD_DESC": "Omschr",
    "FIELD_NAME": "ATS_DESC",
    "DBF_NAME": "ADM_LIST",
    "FIELD_LEN": 40,
    "FIELD_TYPE": "C",
    "INP_MAND": false,
    "FLD_FMT": "",
    "FLD_MASK": "",
    "COM_BLK": false,
    "CNG_DATE": "",
    "CNG_NR": 0,
    "CNG_USR": "",
    "INP_DATE": "",
    "PKY_TBL": "",
    "REC_CUST": false,
    "DCT_FLD_Id": 13
  },
  {
    "FLD_DESC": "Extra veld",
    "FIELD_NAME": "ATS_EXTRA",
    "DBF_NAME": "ADM_LIST",
    "FIELD_LEN": 10,
    "FIELD_TYPE": "C",
    "INP_MAND": false,
    "FLD_FMT": "",
    "FLD_MASK": "",
    "COM_BLK": false,
    "CNG_DATE": "",
    "CNG_NR": 0,
    "CNG_USR": "",
    "INP_DATE": "",
    "PKY_TBL": "",
    "REC_CUST": false,
    "DCT_FLD_Id": 14
  },
  {
    "FLD_DESC": "Vestigingscode",
    "FIELD_NAME": "ATS_LOC",
    "DBF_NAME": "ADM_LIST",
    "FIELD_LEN": 10,
    "FIELD_TYPE": "C",
    "INP_MAND": false,
    "FLD_FMT": "",
    "FLD_MASK": "",
    "COM_BLK": false,
    "CNG_DATE": "",
    "CNG_NR": 0,
    "CNG_USR": "",
    "INP_DATE": "",
    "PKY_TBL": "",
    "REC_CUST": false,
    "DCT_FLD_Id": 15
  },
  {
    "FLD_DESC": "Boekjaar",
    "FIELD_NAME": "ATS_YEAR",
    "DBF_NAME": "ADM_LIST",
    "FIELD_LEN": 10,
    "FIELD_TYPE": "C",
    "INP_MAND": false,
    "FLD_FMT": "",
    "FLD_MASK": "",
    "COM_BLK": false,
    "CNG_DATE": "",
    "CNG_NR": 0,
    "CNG_USR": "",
    "INP_DATE": "",
    "PKY_TBL": "",
    "REC_CUST": false,
    "DCT_FLD_Id": 16
  },
  {
    "FLD_DESC": "Geblokkeerd op datum/tijd",
    "FIELD_NAME": "BLCK_DATE",
    "DBF_NAME": "ADM_LIST",
    "FIELD_LEN": 8,
    "FIELD_TYPE": "T",
    "INP_MAND": false,
    "FLD_FMT": "",
    "FLD_MASK": "",
    "COM_BLK": false,
    "CNG_DATE": "",
    "CNG_NR": 0,
    "CNG_USR": "",
    "INP_DATE": "",
    "PKY_TBL": "",
    "REC_CUST": false,
    "DCT_FLD_Id": 17
  },
  {
    "FLD_DESC": "Geblokkeerd door gebruiker",
    "FIELD_NAME": "BLCK_USER",
    "DBF_NAME": "ADM_LIST",
    "FIELD_LEN": 20,
    "FIELD_TYPE": "C",
    "INP_MAND": false,
    "FLD_FMT": "!",
    "FLD_MASK": "",
    "COM_BLK": false,
    "CNG_DATE": "",
    "CNG_NR": 0,
    "CNG_USR": "",
    "INP_DATE": "",
    "PKY_TBL": "",
    "REC_CUST": false,
    "DCT_FLD_Id": 18
  },
  {
    "FLD_DESC": "Geblokkeerd (pictogram)",
    "FIELD_NAME": "BLCK_USRV",
    "DBF_NAME": "ADM_LIST",
    "FIELD_LEN": 10,
    "FIELD_TYPE": "C",
    "INP_MAND": false,
    "FLD_FMT": "!",
    "FLD_MASK": "",
    "COM_BLK": false,
    "CNG_DATE": "",
    "CNG_NR": 0,
    "CNG_USR": "",
    "INP_DATE": "",
    "PKY_TBL": "",
    "REC_CUST": false,
    "DCT_FLD_Id": 19
  },
  {
    "FLD_DESC": "Datum laatste boeking",
    "FIELD_NAME": "BOOK_DATE",
    "DBF_NAME": "ADM_LIST",
    "FIELD_LEN": 8,
    "FIELD_TYPE": "T",
    "INP_MAND": false,
    "FLD_FMT": "",
    "FLD_MASK": "",
    "COM_BLK": false,
    "CNG_DATE": "",
    "CNG_NR": 0,
    "CNG_USR": "",
    "INP_DATE": "",
    "PKY_TBL": "",
    "REC_CUST": false,
    "DCT_FLD_Id": 20
  },
  {
    "FLD_DESC": "Meegenomen op datum/tijd",
    "FIELD_NAME": "CICO_DATE",
    "DBF_NAME": "ADM_LIST",
    "FIELD_LEN": 8,
    "FIELD_TYPE": "T",
    "INP_MAND": false,
    "FLD_FMT": "",
    "FLD_MASK": "",
    "COM_BLK": false,
    "CNG_DATE": "",
    "CNG_NR": 0,
    "CNG_USR": "",
    "INP_DATE": "",
    "PKY_TBL": "",
    "REC_CUST": false,
    "DCT_FLD_Id": 21
  },
  {
    "FLD_DESC": "Meegenomen door gebruiker",
    "FIELD_NAME": "CICO_USR",
    "DBF_NAME": "ADM_LIST",
    "FIELD_LEN": 20,
    "FIELD_TYPE": "C",
    "INP_MAND": false,
    "FLD_FMT": "!",
    "FLD_MASK": "",
    "COM_BLK": false,
    "CNG_DATE": "",
    "CNG_NR": 0,
    "CNG_USR": "",
    "INP_DATE": "",
    "PKY_TBL": "",
    "REC_CUST": false,
    "DCT_FLD_Id": 22
  },
  {
    "FLD_DESC": "Wijzigingsdatum",
    "FIELD_NAME": "CNG_DATE",
    "DBF_NAME": "ADM_LIST",
    "FIELD_LEN": 8,
    "FIELD_TYPE": "T",
    "INP_MAND": false,
    "FLD_FMT": "",
    "FLD_MASK": "",
    "COM_BLK": true,
    "CNG_DATE": "",
    "CNG_NR": 0,
    "CNG_USR": "",
    "INP_DATE": "",
    "PKY_TBL": "",
    "REC_CUST": false,
    "DCT_FLD_Id": 23
  },
  {
    "FLD_DESC": "Wijzignummer",
    "FIELD_NAME": "CNG_NR",
    "DBF_NAME": "ADM_LIST",
    "FIELD_LEN": 4,
    "FIELD_TYPE": "I",
    "INP_MAND": false,
    "FLD_FMT": "",
    "FLD_MASK": "",
    "COM_BLK": true,
    "CNG_DATE": "",
    "CNG_NR": 0,
    "CNG_USR": "",
    "INP_DATE": "",
    "PKY_TBL": "",
    "REC_CUST": false,
    "DCT_FLD_Id": 24
  },
  {
    "FLD_DESC": "Medewerker laatste wijziging",
    "FIELD_NAME": "CNG_USR",
    "DBF_NAME": "ADM_LIST",
    "FIELD_LEN": 20,
    "FIELD_TYPE": "C",
    "INP_MAND": false,
    "FLD_FMT": "!",
    "FLD_MASK": "",
    "COM_BLK": true,
    "CNG_DATE": "",
    "CNG_NR": 0,
    "CNG_USR": "",
    "INP_DATE": "",
    "PKY_TBL": "",
    "REC_CUST": false,
    "DCT_FLD_Id": 25
  },
  {
    "FLD_DESC": "Deelnamepercentage holding",
    "FIELD_NAME": "CNL_PCT",
    "DBF_NAME": "ADM_LIST",
    "FIELD_LEN": 12,
    "FIELD_TYPE": "N",
    "INP_MAND": false,
    "FLD_FMT": "",
    "FLD_MASK": "",
    "COM_BLK": false,
    "CNG_DATE": "",
    "CNG_NR": 0,
    "CNG_USR": "",
    "INP_DATE": "",
    "PKY_TBL": "",
    "REC_CUST": false,
    "DCT_FLD_Id": 26
  },
  {
    "FLD_DESC": "Deelnamepercentage holding intern",
    "FIELD_NAME": "CNL_PCT2",
    "DBF_NAME": "ADM_LIST",
    "FIELD_LEN": 12,
    "FIELD_TYPE": "N",
    "INP_MAND": false,
    "FLD_FMT": "",
    "FLD_MASK": "",
    "COM_BLK": false,
    "CNG_DATE": "",
    "CNG_NR": 0,
    "CNG_USR": "",
    "INP_DATE": "",
    "PKY_TBL": "",
    "REC_CUST": false,
    "DCT_FLD_Id": 27
  },
  {
    "FLD_DESC": "Databasenaam administratie",
    "FIELD_NAME": "DBC_NAME",
    "DBF_NAME": "ADM_LIST",
    "FIELD_LEN": 8,
    "FIELD_TYPE": "C",
    "INP_MAND": true,
    "FLD_FMT": "!",
    "FLD_MASK": "",
    "COM_BLK": false,
    "CNG_DATE": "",
    "CNG_NR": 0,
    "CNG_USR": "",
    "INP_DATE": "",
    "PKY_TBL": "",
    "REC_CUST": false,
    "DCT_FLD_Id": 28
  },
  {
    "FLD_DESC": "Invoerdatum",
    "FIELD_NAME": "INP_DATE",
    "DBF_NAME": "ADM_LIST",
    "FIELD_LEN": 8,
    "FIELD_TYPE": "T",
    "INP_MAND": false,
    "FLD_FMT": "",
    "FLD_MASK": "",
    "COM_BLK": true,
    "CNG_DATE": "",
    "CNG_NR": 0,
    "CNG_USR": "",
    "INP_DATE": "",
    "PKY_TBL": "",
    "REC_CUST": false,
    "DCT_FLD_Id": 29
  },
  {
    "FLD_DESC": "Invoermedewerker",
    "FIELD_NAME": "INP_USR",
    "DBF_NAME": "ADM_LIST",
    "FIELD_LEN": 20,
    "FIELD_TYPE": "C",
    "INP_MAND": false,
    "FLD_FMT": "!",
    "FLD_MASK": "",
    "COM_BLK": true,
    "CNG_DATE": "",
    "CNG_NR": 0,
    "CNG_USR": "",
    "INP_DATE": "",
    "PKY_TBL": "",
    "REC_CUST": false,
    "DCT_FLD_Id": 30
  },
  {
    "FLD_DESC": "Installatie",
    "FIELD_NAME": "INST_CODE",
    "DBF_NAME": "ADM_LIST",
    "FIELD_LEN": 5,
    "FIELD_TYPE": "C",
    "INP_MAND": false,
    "FLD_FMT": "!",
    "FLD_MASK": "",
    "COM_BLK": false,
    "CNG_DATE": "",
    "CNG_NR": 0,
    "CNG_USR": "",
    "INP_DATE": "",
    "PKY_TBL": "",
    "REC_CUST": false,
    "DCT_FLD_Id": 31
  },
  {
    "FLD_DESC": "Licentie gewijzigd",
    "FIELD_NAME": "LIC_CNG",
    "DBF_NAME": "ADM_LIST",
    "FIELD_LEN": 1,
    "FIELD_TYPE": "L",
    "INP_MAND": false,
    "FLD_FMT": "",
    "FLD_MASK": "",
    "COM_BLK": false,
    "CNG_DATE": "",
    "CNG_NR": 0,
    "CNG_USR": "",
    "INP_DATE": "",
    "PKY_TBL": "",
    "REC_CUST": false,
    "DCT_FLD_Id": 32
  },
  {
    "FLD_DESC": "Geblokkeerd voor multicliënt telebankieren",
    "FIELD_NAME": "MC_BLOCK",
    "DBF_NAME": "ADM_LIST",
    "FIELD_LEN": 1,
    "FIELD_TYPE": "L",
    "INP_MAND": false,
    "FLD_FMT": "",
    "FLD_MASK": "",
    "COM_BLK": false,
    "CNG_DATE": "",
    "CNG_NR": 0,
    "CNG_USR": "",
    "INP_DATE": "",
    "PKY_TBL": "",
    "REC_CUST": false,
    "DCT_FLD_Id": 33
  },
  {
    "FLD_DESC": "Berichtbestemming",
    "FIELD_NAME": "MSG_DEST",
    "DBF_NAME": "ADM_LIST",
    "FIELD_LEN": 40,
    "FIELD_TYPE": "C",
    "INP_MAND": false,
    "FLD_FMT": "!",
    "FLD_MASK": "",
    "COM_BLK": false,
    "CNG_DATE": "",
    "CNG_NR": 0,
    "CNG_USR": "",
    "INP_DATE": "",
    "PKY_TBL": "",
    "REC_CUST": false,
    "DCT_FLD_Id": 34
  },
  {
    "FLD_DESC": "Berichtklasse",
    "FIELD_NAME": "MSG_STGY",
    "DBF_NAME": "ADM_LIST",
    "FIELD_LEN": 25,
    "FIELD_TYPE": "C",
    "INP_MAND": false,
    "FLD_FMT": "!",
    "FLD_MASK": "",
    "COM_BLK": false,
    "CNG_DATE": "",
    "CNG_NR": 0,
    "CNG_USR": "",
    "INP_DATE": "",
    "PKY_TBL": "",
    "REC_CUST": false,
    "DCT_FLD_Id": 35
  },
  {
    "FLD_DESC": "Netwerkgebruik administratie",
    "FIELD_NAME": "NET_USE",
    "DBF_NAME": "ADM_LIST",
    "FIELD_LEN": 1,
    "FIELD_TYPE": "L",
    "INP_MAND": false,
    "FLD_FMT": "",
    "FLD_MASK": "",
    "COM_BLK": false,
    "CNG_DATE": "",
    "CNG_NR": 0,
    "CNG_USR": "",
    "INP_DATE": "",
    "PKY_TBL": "",
    "REC_CUST": false,
    "DCT_FLD_Id": 36
  },
  {
    "FLD_DESC": "Administratie moet worden georganiseerd",
    "FIELD_NAME": "ORG_ADM",
    "DBF_NAME": "ADM_LIST",
    "FIELD_LEN": 1,
    "FIELD_TYPE": "L",
    "INP_MAND": false,
    "FLD_FMT": "",
    "FLD_MASK": "",
    "COM_BLK": false,
    "CNG_DATE": "",
    "CNG_NR": 0,
    "CNG_USR": "",
    "INP_DATE": "",
    "PKY_TBL": "",
    "REC_CUST": false,
    "DCT_FLD_Id": 37
  },
  {
    "FLD_DESC": "Geblokkeerd voor alerts",
    "FIELD_NAME": "SCHED_BLK",
    "DBF_NAME": "ADM_LIST",
    "FIELD_LEN": 1,
    "FIELD_TYPE": "L",
    "INP_MAND": false,
    "FLD_FMT": "",
    "FLD_MASK": "",
    "COM_BLK": false,
    "CNG_DATE": "",
    "CNG_NR": 0,
    "CNG_USR": "",
    "INP_DATE": "",
    "PKY_TBL": "",
    "REC_CUST": false,
    "DCT_FLD_Id": 38
  },
  {
    "FLD_DESC": "Stamgegevens uitwisselen",
    "FIELD_NAME": "SYNC_LOG",
    "DBF_NAME": "ADM_LIST",
    "FIELD_LEN": 1,
    "FIELD_TYPE": "L",
    "INP_MAND": false,
    "FLD_FMT": "",
    "FLD_MASK": "",
    "COM_BLK": false,
    "CNG_DATE": "",
    "CNG_NR": 0,
    "CNG_USR": "",
    "INP_DATE": "",
    "PKY_TBL": "",
    "REC_CUST": false,
    "DCT_FLD_Id": 39
  }
]
